Wsorter/__init__.py
Wsorter/sorter.py
Wsorter-0.1.dist-info/METADATA
Wsorter-0.1.dist-info/WHEEL
Wsorter-0.1.dist-info/top_level.txt
Wsorter-0.1.dist-info/RECORD
