Metadata-Version: 2.1
Name: Wsorter
Version: 0.1
Summary: A simple library to sort words alphabetically
Author: chinmay
Author-email: lawd7131@gmail.com
License: MIT
Classifier: Programming Language :: Python :: 3
Classifier: License :: OSI Approved :: MIT License
Classifier: Operating System :: OS Independent
Requires-Python: >=3.6
